sysinsight/__init__.py
sysinsight/__main__.py
sysinsight/sysinsight.py
system_insight-1.2.7.data/scripts/sysinsight.py
system_insight-1.2.7.dist-info/METADATA
system_insight-1.2.7.dist-info/WHEEL
system_insight-1.2.7.dist-info/entry_points.txt
system_insight-1.2.7.dist-info/top_level.txt
system_insight-1.2.7.dist-info/RECORD
