Metadata-Version: 2.1
Name: system-insight
Version: 1.2.7
Summary: A simple tool for quickly gathering information about the current state of the system.
Home-page: https://github.com/AquaQuokka/system-insight
Author: AquaQuokka
License: BSD-3-Clause
Requires-Dist: psutil
